{"is_source_file": true, "format": "JavaScript", "description": "This file provides utility functions for managing authentication tokens in local storage, including setting, retrieving, and clearing a token identified by a specific key.", "external_files": [], "external_methods": [], "published": ["setToken", "getToken", "clearToken"], "classes": [], "methods": [{"name": "setToken(token)", "description": "Stores the provided token in local storage under a specific key.", "scope": "", "scopeKind": ""}, {"name": "getToken()", "description": "Retrieves the token stored in local storage under the specific key.", "scope": "", "scopeKind": ""}, {"name": "clearToken()", "description": "Removes the token from local storage, effectively clearing the authentication token.", "scope": "", "scopeKind": ""}], "calls": ["localStorage.setItem", "localStorage.getItem", "localStorage.removeItem"], "search-terms": ["auth", "token", "localStorage", "auth.js", "notes_token", "token management", "local storage utilities"], "state": 2, "file_id": 19, "knowledge_revision": 40, "git_revision": "", "ctags": [{"_type": "tag", "name": "TOKEN_KEY", "path": "/home/kavia/workspace/code-generation/personal-notes-manager-6607-6656/notes_frontend/src/utils/auth.js", "pattern": "/^const TOKEN_KEY = 'notes_token';$/", "language": "JavaScript", "kind": "constant"}, {"_type": "tag", "name": "clearToken", "path": "/home/kavia/workspace/code-generation/personal-notes-manager-6607-6656/notes_frontend/src/utils/auth.js", "pattern": "/^export function clearToken() {$/", "language": "JavaScript", "kind": "function", "signature": "()"}, {"_type": "tag", "name": "getToken", "path": "/home/kavia/workspace/code-generation/personal-notes-manager-6607-6656/notes_frontend/src/utils/auth.js", "pattern": "/^export function getToken() {$/", "language": "JavaScript", "kind": "function", "signature": "()"}, {"_type": "tag", "name": "setToken", "path": "/home/kavia/workspace/code-generation/personal-notes-manager-6607-6656/notes_frontend/src/utils/auth.js", "pattern": "/^export function setToken(token) {$/", "language": "JavaScript", "kind": "function", "signature": "(token)"}], "hash": "1a85a3ea309cbf2f0179996ff4efb0a3", "format-version": 4, "code-base-name": "notes_frontend", "filename": "notes_frontend/src/utils/auth.js", "revision_history": [{"40": ""}]}